stringmetrics-2.1.1.dist-info/METADATA
stringmetrics-2.1.1.dist-info/WHEEL
stringmetrics-2.1.1.dist-info/license_files/LICENSE
stringmetrics/py.typed
stringmetrics/__init__.py
stringmetrics/stringmetrics.pyi
stringmetrics/stringmetrics.cpython-37m-x86_64-linux-gnu.so
stringmetrics-2.1.1.dist-info/RECORD
