Metadata-Version: 2.1
Name: stringmetrics
Version: 2.1.1
Classifier: Programming Language :: Rust
Classifier: Programming Language :: Python :: Implementation :: CPython
Classifier: Programming Language :: Python :: Implementation :: PyPy
License-File: LICENSE
Summary: A fast library for string metrics, including Levenshtein distance
Requires-Python: >=3.7
